[
   {
                "Id": 0,
                "Nombre": "Total",
                "SonDatosNumericos": true,
                "Fuente": "INE",
                "Clasificacion": null,
                "Unidad": "Habitantes",
                "Escala": "Unidades",
                "EscalaFactorPotencia10": 0,
                "Datos": [
                    {
                        "Agno": 2020,
                        "Periodo": "Año",
                        "Parametro": "2020",
                        "Valor": 47329981.08819,
                        "Estado": null,
                        "Notas": null
                    },
                    {
                        "Agno": 2021,
                        "Periodo": "Año",
                        "Parametro": "2021",
                        "Valor": 47326957.58712,
                        "Estado": null,
                        "Notas": null
                    },
                    {
                        "Agno": 2022,
                        "Periodo": "Año",
                        "Parametro": "2022",
                        "Valor": 47353590.244928,
                        "Estado": null,
                        "Notas": null
                    },
                    {
                        "Agno": 2023,
                        "Periodo": "Año",
                        "Parametro": "2023",
                        "Valor": 47381954.508527,
                        "Estado": null,
                        "Notas": null
                    },
                    {
                        "Agno": 2024,
                        "Periodo": "Año",
                        "Parametro": "2024",
                        "Valor": 47413275.143226,
                        "Estado": null,
                        "Notas": null
                    },
                    {
                        "Agno": 2025,
                        "Periodo": "Año",
                        "Parametro": "2025",
                        "Valor": 47449884.290086,
                        "Estado": null,
                        "Notas": null
                    },
                    {
                        "Agno": 2026,
                        "Periodo": "Año",
                        "Parametro": "2026",
                        "Valor": 47492624.47344,
                        "Estado": null,
                        "Notas": null
                    },
                    {
                        "Agno": 2027,
                        "Periodo": "Año",
                        "Parametro": "2027",
                        "Valor": 47543131.608132,
                        "Estado": null,
                        "Notas": null
                    },
                    {
                        "Agno": 2028,
                        "Periodo": "Año",
                        "Parametro": "2028",
                        "Valor": 47601835.193319,
                        "Estado": null,
                        "Notas": null
                    },
                    {
                        "Agno": 2029,
                        "Periodo": "Año",
                        "Parametro": "2029",
                        "Valor": 47670571.140153,
                        "Estado": null,
                        "Notas": null
                    },
                    {
                        "Agno": 2030,
                        "Periodo": "Año",
                        "Parametro": "2030",
                        "Valor": 47749006.851181,
                        "Estado": null,
                        "Notas": null
                    },
                    {
                        "Agno": 2031,
                        "Periodo": "Año",
                        "Parametro": "2031",
                        "Valor": 47837800.990217,
                        "Estado": null,
                        "Notas": null
                    },
                    {
                        "Agno": 2032,
                        "Periodo": "Año",
                        "Parametro": "2032",
                        "Valor": 47937659.533489,
                        "Estado": null,
                        "Notas": null
                    },
                    {
                        "Agno": 2033,
                        "Periodo": "Año",
                        "Parametro": "2033",
                        "Valor": 48046647.009684,
                        "Estado": null,
                        "Notas": null
                    },
                    {
                        "Agno": 2034,
                        "Periodo": "Año",
                        "Parametro": "2034",
                        "Valor": 48163458.881234,
                        "Estado": null,
                        "Notas": null
                    },
                    {
                        "Agno": 2035,
                        "Periodo": "Año",
                        "Parametro": "2035",
                        "Valor": 48284478.509635,
                        "Estado": null,
                        "Notas": null
                    },
                    {
                        "Agno": 2036,
                        "Periodo": "Año",
                        "Parametro": "2036",
                        "Valor": 48406971.153359,
                        "Estado": null,
                        "Notas": null
                    },
                    {
                        "Agno": 2037,
                        "Periodo": "Año",
                        "Parametro": "2037",
                        "Valor": 48530640.045944,
                        "Estado": null,
                        "Notas": null
                    },
                    {
                        "Agno": 2038,
                        "Periodo": "Año",
                        "Parametro": "2038",
                        "Valor": 48655242.943804,
                        "Estado": null,
                        "Notas": null
                    },
                    {
                        "Agno": 2039,
                        "Periodo": "Año",
                        "Parametro": "2039",
                        "Valor": 48780307.495667,
                        "Estado": null,
                        "Notas": null
                    },
                    {
                        "Agno": 2040,
                        "Periodo": "Año",
                        "Parametro": "2040",
                        "Valor": 48905119.679483,
                        "Estado": null,
                        "Notas": null
                    },
                    {
                        "Agno": 2041,
                        "Periodo": "Año",
                        "Parametro": "2041",
                        "Valor": 49028095.648371,
                        "Estado": null,
                        "Notas": null
                    },
                    {
                        "Agno": 2042,
                        "Periodo": "Año",
                        "Parametro": "2042",
                        "Valor": 49148869.651787,
                        "Estado": null,
                        "Notas": null
                    },
                    {
                        "Agno": 2043,
                        "Periodo": "Año",
                        "Parametro": "2043",
                        "Valor": 49266205.275644,
                        "Estado": null,
                        "Notas": null
                    },
                    {
                        "Agno": 2044,
                        "Periodo": "Año",
                        "Parametro": "2044",
                        "Valor": 49378820.778701,
                        "Estado": null,
                        "Notas": null
                    },
                    {
                        "Agno": 2045,
                        "Periodo": "Año",
                        "Parametro": "2045",
                        "Valor": 49485810.505834,
                        "Estado": null,
                        "Notas": null
                    },
                    {
                        "Agno": 2046,
                        "Periodo": "Año",
                        "Parametro": "2046",
                        "Valor": 49586245.581539,
                        "Estado": null,
                        "Notas": null
                    },
                    {
                        "Agno": 2047,
                        "Periodo": "Año",
                        "Parametro": "2047",
                        "Valor": 49679558.244063,
                        "Estado": null,
                        "Notas": null
                    },
                    {
                        "Agno": 2048,
                        "Periodo": "Año",
                        "Parametro": "2048",
                        "Valor": 49765016.942511,
                        "Estado": null,
                        "Notas": null
                    },
                    {
                        "Agno": 2049,
                        "Periodo": "Año",
                        "Parametro": "2049",
                        "Valor": 49842029.693808,
                        "Estado": null,
                        "Notas": null
                    },
                    {
                        "Agno": 2050,
                        "Periodo": "Año",
                        "Parametro": "2050",
                        "Valor": 49910653.375213,
                        "Estado": null,
                        "Notas": null
                    },
                    {
                        "Agno": 2051,
                        "Periodo": "Año",
                        "Parametro": "2051",
                        "Valor": 49971012.641566,
                        "Estado": null,
                        "Notas": null
                    },
                    {
                        "Agno": 2052,
                        "Periodo": "Año",
                        "Parametro": "2052",
                        "Valor": 50023223.484772,
                        "Estado": null,
                        "Notas": null
                    },
                    {
                        "Agno": 2053,
                        "Periodo": "Año",
                        "Parametro": "2053",
                        "Valor": 50067569.294122,
                        "Estado": null,
                        "Notas": null
                    },
                    {
                        "Agno": 2054,
                        "Periodo": "Año",
                        "Parametro": "2054",
                        "Valor": 50104727.063051,
                        "Estado": null,
                        "Notas": null
                    },
                    {
                        "Agno": 2055,
                        "Periodo": "Año",
                        "Parametro": "2055",
                        "Valor": 50135516.326859,
                        "Estado": null,
                        "Notas": null
                    },
                    {
                        "Agno": 2056,
                        "Periodo": "Año",
                        "Parametro": "2056",
                        "Valor": 50160764.467356,
                        "Estado": null,
                        "Notas": null
                    },
                    {
                        "Agno": 2057,
                        "Periodo": "Año",
                        "Parametro": "2057",
                        "Valor": 50181516.576966,
                        "Estado": null,
                        "Notas": null
                    },
                    {
                        "Agno": 2058,
                        "Periodo": "Año",
                        "Parametro": "2058",
                        "Valor": 50198810.006492,
                        "Estado": null,
                        "Notas": null
                    },
                    {
                        "Agno": 2059,
                        "Periodo": "Año",
                        "Parametro": "2059",
                        "Valor": 50213948.5007,
                        "Estado": null,
                        "Notas": null
                    },
                    {
                        "Agno": 2060,
                        "Periodo": "Año",
                        "Parametro": "2060",
                        "Valor": 50228241.397269,
                        "Estado": null,
                        "Notas": null
                    },
                    {
                        "Agno": 2061,
                        "Periodo": "Año",
                        "Parametro": "2061",
                        "Valor": 50242967.273362,
                        "Estado": null,
                        "Notas": null
                    },
                    {
                        "Agno": 2062,
                        "Periodo": "Año",
                        "Parametro": "2062",
                        "Valor": 50259480.103202,
                        "Estado": null,
                        "Notas": null
                    },
                    {
                        "Agno": 2063,
                        "Periodo": "Año",
                        "Parametro": "2063",
                        "Valor": 50278965.477844,
                        "Estado": null,
                        "Notas": null
                    },
                    {
                        "Agno": 2064,
                        "Periodo": "Año",
                        "Parametro": "2064",
                        "Valor": 50302555.060751,
                        "Estado": null,
                        "Notas": null
                    },
                    {
                        "Agno": 2065,
                        "Periodo": "Año",
                        "Parametro": "2065",
                        "Valor": 50331305.500926,
                        "Estado": null,
                        "Notas": null
                    },
                    {
                        "Agno": 2066,
                        "Periodo": "Año",
                        "Parametro": "2066",
                        "Valor": 50366479.869665,
                        "Estado": null,
                        "Notas": null
                    },
                    {
                        "Agno": 2067,
                        "Periodo": "Año",
                        "Parametro": "2067",
                        "Valor": 50409088.626491,
                        "Estado": null,
                        "Notas": null
                    },
                    {
                        "Agno": 2068,
                        "Periodo": "Año",
                        "Parametro": "2068",
                        "Valor": 50459965.808064,
                        "Estado": null,
                        "Notas": null
                    },
                    {
                        "Agno": 2069,
                        "Periodo": "Año",
                        "Parametro": "2069",
                        "Valor": 50519995.159957,
                        "Estado": null,
                        "Notas": null
                    },
                    {
                        "Agno": 2070,
                        "Periodo": "Año",
                        "Parametro": "2070",
                        "Valor": 50589810.594628,
                        "Estado": null,
                        "Notas": null
                    }
]
